fxpkg/__init__.py
fxpkg/buildctx.py
fxpkg/exception.py
fxpkg/internal.py
fxpkg/common/__init__.py
fxpkg/common/constants.py
fxpkg/common/dataclass.py
fxpkg/common/helpler.py
fxpkg/common/types.py
fxpkg/core/__init__.py
fxpkg/core/buildexec.py
fxpkg/core/importpkg.py
fxpkg/db/__init__.py
fxpkg/db/installInfo.py
fxpkg/db/types.py
fxpkg/db/util.py
fxpkg/helpler/__init__.py
fxpkg/helpler/build.py
fxpkg/helpler/cmake.py
fxpkg/helpler/msvc.py
fxpkg/helpler/version.py
fxpkg/interface/__init__.py
fxpkg/interface/package.py
fxpkg/interface/version.py
fxpkg/package/__init__.py
fxpkg/pkgbase/__init__.py
fxpkg/pkgbase/base.py
fxpkg/pkgbase/cmake.py
fxpkg/pkgbase/gpm.py
fxpkg/util/__init__.py
fxpkg/util/async_pipeline.py
fxpkg/util/async_util.py
fxpkg/util/coro_queue.py
fxpkg/util/dag.py
fxpkg/util/inf.py
fxpkg/util/path.py
fxpkg/util/proxy.py
fxpkg-0.0.0.dist-info/LICENSE.txt
fxpkg-0.0.0.dist-info/METADATA
fxpkg-0.0.0.dist-info/WHEEL
fxpkg-0.0.0.dist-info/top_level.txt
fxpkg-0.0.0.dist-info/RECORD
